LICENSE
README.md
pyproject.toml
setup.py
flake8_tkinter/__init__.py
flake8_tkinter/constants.py
flake8_tkinter/messages.py
flake8_tkinter/utils.py
flake8_tkinter/visitor.py
flake8_tkinter.egg-info/PKG-INFO
flake8_tkinter.egg-info/SOURCES.txt
flake8_tkinter.egg-info/dependency_links.txt
flake8_tkinter.egg-info/entry_points.txt
flake8_tkinter.egg-info/requires.txt
flake8_tkinter.egg-info/top_level.txt
flake8_tkinter/rules/ast_assign.py
flake8_tkinter/rules/ast_attribute.py
flake8_tkinter/rules/ast_call.py
flake8_tkinter/rules/ast_import.py
flake8_tkinter/rules/ast_import_from.py
flake8_tkinter/rules/ast_loop.py