Metadata-Version: 2.1
Name: flake8-tkinter
Version: 0.6.0
Summary: A flake8 plugin that helps you write better Tkinter code
Home-page: https://github.com/rdbende/flake8-tkinter
Author: rdbende
Author-email: rdbende@gmail.com
License: MIT license
Project-URL: Tracker, https://github.com/rdbende/flake8-tkinter/issues
Platform: UNKNOWN
Classifier: Framework :: Flake8
Classifier: Environment :: Console
Classifier: Intended Audience :: Developers
Classifier: License :: OSI Approved :: MIT License
Classifier: Programming Language :: Python :: 3 :: Only
Classifier: Programming Language :: Python :: 3.7
Classifier: Programming Language :: Python :: 3.8
Classifier: Programming Language :: Python :: 3.9
Classifier: Programming Language :: Python :: 3.10
Classifier: Programming Language :: Python :: 3.11
Classifier: Topic :: Software Development :: Libraries :: Python Modules
Classifier: Topic :: Software Development :: Quality Assurance
Requires-Python: >=3.7
License-File: LICENSE
